[
  {
    "year": 1975,
    "p1": "Billie Jean King",
    "p2": "Evonne Goolagong"
  },
  {
    "year": 1976,
    "p1": "Chris Evert",
    "p2": "Evonne Goolagong"
  },
  {
    "year": 1977,
    "p1": "Virginia Wade",
    "p2": "Betty Stove"
  },
  {
    "year": 1978,
    "p1": "Martina Navratilova",
    "p2": "Chris Evert"
  },
  {
    "year": 1979,
    "p1": "Martina Navratilova",
    "p2": "Chris Evert"
  },
  {
    "year": 1980,
    "p1": "Evonne Goolagong Cawley",
    "p2": "Chris Evert"
  },
  {
    "year": 1981,
    "p1": "Chris Evert",
    "p2": "Hana Mandlikova"
  },
  {
    "year": 1982,
    "p1": "Martina Navratilova",
    "p2": "Chris Evert"
  },
  {
    "year": 1983,
    "p1": "Martina Navratilova",
    "p2": "Andrea Jaeger"
  },
  {
    "year": 1984,
    "p1": "Martina Navratilova",
    "p2": "Chris Evert"
  },
  {
    "year": 1985,
    "p1": "Martina Navratilova",
    "p2": "Chris Evert"
  },
  {
    "year": 1986,
    "p1": "Martina Navratilova",
    "p2": "Hana Mandlikova"
  },
  {
    "year": 1987,
    "p1": "Martina Navratilova",
    "p2": "Steffi Graf"
  },
  {
    "year": 1988,
    "p1": "Steffi Graf",
    "p2": "Martina Navratilova"
  },
  {
    "year": 1989,
    "p1": "Steffi Graf",
    "p2": "Martina Navratilova"
  },
  {
    "year": 1990,
    "p1": "Martina Navratilova",
    "p2": "Zina Garrison"
  },
  {
    "year": 1991,
    "p1": "Steffi Graf",
    "p2": "Gabriela Sabatini"
  },
  {
    "year": 1992,
    "p1": "Steffi Graf",
    "p2": "Monica Seles"
  },
  {
    "year": 1993,
    "p1": "Steffi Graf",
    "p2": "Jana Novotna"
  },
  {
    "year": 1994,
    "p1": "Conchita Martinez",
    "p2": "Martina Navratilova"
  },
  {
    "year": 1995,
    "p1": "Steffi Graf",
    "p2": "Arantxa Sanchez Vicario"
  },
  {
    "year": 1996,
    "p1": "Steffi Graf",
    "p2": "Arantxa Sanchez Vicario"
  },
  {
    "year": 1997,
    "p1": "Martina Hingis",
    "p2": "Jana Novotna"
  },
  {
    "year": 1998,
    "p1": "Jana Novotna",
    "p2": "Nathalie Tauziat"
  },
  {
    "year": 1999,
    "p1": "Lindsay Davenport",
    "p2": "Steffi Graf"
  },
  {
    "year": 2000,
    "p1": "Venus Williams",
    "p2": "Lindsay Davenport"
  },
  {
    "year": 2001,
    "p1": "Venus Williams",
    "p2": "Justine Henin"
  },
  {
    "year": 2002,
    "p1": "Serena Williams",
    "p2": "Venus Williams"
  },
  {
    "year": 2003,
    "p1": "Serena Williams",
    "p2": "Venus Williams"
  },
  {
    "year": 2004,
    "p1": "Maria Sharapova",
    "p2": "Serena Williams"
  },
  {
    "year": 2005,
    "p1": "Venus Williams",
    "p2": "Lindsay Davenport"
  },
  {
    "year": 2006,
    "p1": "Amelie Mauresmo",
    "p2": "Justine Henin"
  },
  {
    "year": 2007,
    "p1": "Venus Williams",
    "p2": "Marion Bartoli"
  },
  {
    "year": 2008,
    "p1": "Venus Williams",
    "p2": "Serena Williams"
  },
  {
    "year": 2009,
    "p1": "Serena Williams",
    "p2": "Venus Williams"
  },
  {
    "year": 2010,
    "p1": "Serena Williams",
    "p2": "Vera Zvonareva"
  },
  {
    "year": 2011,
    "p1": "Petra Kvitova",
    "p2": "Maria Sharapova"
  },
  {
    "year": 2012,
    "p1": "Serena Williams",
    "p2": "Agnieszka Radwanska"
  },
  {
    "year": 2013,
    "p1": "Marion Bartoli",
    "p2": "Sabine Lisicki"
  },
  {
    "year": 2014,
    "p1": "Petra Kvitova",
    "p2": "Eugenie Bouchard"
  },
  {
    "year": 2015,
    "p1": "Serena Williams",
    "p2": "Garbine Muguruza"
  },
  {
    "year": 2016,
    "p1": "Serena Williams",
    "p2": "Angelique Kerber"
  },
  {
    "year": 2017,
    "p1": "Garbine Muguruza",
    "p2": "Venus Williams"
  },
  {
    "year": 2018,
    "p1": "Angelique Kerber",
    "p2": "Serena Williams"
  },
  {
    "year": 2019,
    "p1": "Simona Halep",
    "p2": "Serena Williams"
  },
  {
    "year": 2021,
    "p1": "Ashleigh Barty",
    "p2": "Karolina Pliskova"
  },
  {
    "year": 2022,
    "p1": "Elena Rybakina",
    "p2": "Ons Jabeur"
  },
  {
    "year": 2023,
    "p1": "Marketa Vondrousova",
    "p2": "Ons Jabeur"
  },
  {
    "year": 2024,
    "p1": "Barbora Krejcikova",
    "p2": "Jasmine Paolini"
  },
  {
    "year": 2025,
    "p1": "Iga Swiatek",
    "p2": "Amanda Anisimova"
  }
]